tealight/__init__.py
tealight/version.py
tealight-0.1.0.dist-info/LICENSE
tealight-0.1.0.dist-info/METADATA
tealight-0.1.0.dist-info/WHEEL
tealight-0.1.0.dist-info/top_level.txt
tealight-0.1.0.dist-info/RECORD
