Metadata-Version: 2.1
Name: tealight
Version: 0.1.0
Summary: A very small candlestick library
Home-page: https://github.com/asongtoruin/tealight
Author: Adam Ruszkowski
License: UNKNOWN
Project-URL: Source, https://github.com/asongtoruin/tealight/
Platform: UNKNOWN
Classifier: Development Status :: 3 - Alpha
Classifier: Intended Audience :: Developers
Classifier: License :: OSI Approved :: MIT License
Classifier: Programming Language :: Python :: 3
Classifier: Programming Language :: Python :: 3.6
Classifier: Programming Language :: Python :: 3.7
Classifier: Programming Language :: Python :: 3.8
Classifier: Programming Language :: Python :: 3 :: Only
Requires-Python: >=3.6, <4
Requires-Dist: matplotlib
Requires-Dist: numpy
Requires-Dist: pandas
